scr/__init__.py
scr/__main__.py
scr/args_parsing.py
scr/config_data_class.py
scr/content_match.py
scr/definitions.py
scr/document.py
scr/download_job.py
scr/input_sequences.py
scr/locator.py
scr/match_chain.py
scr/progress_report.py
scr/py.typed
scr/scr.py
scr/scr_context.py
scr/selenium_driver_download.py
scr/selenium_setup.py
scr/utils.py
scr/windows.py
scr/selenium_drivers/chromedriver
scr/selenium_drivers/chromedriver.exe
scr/selenium_drivers/geckodriver
scr/selenium_drivers/geckodriver.exe
scr-0.12.0.dist-info/LICENSE
scr-0.12.0.dist-info/METADATA
scr-0.12.0.dist-info/WHEEL
scr-0.12.0.dist-info/entry_points.txt
scr-0.12.0.dist-info/top_level.txt
scr-0.12.0.dist-info/RECORD
