Metadata-Version: 2.1
Name: scr
Version: 0.12.0
Summary: Command-line Utility for Web Scraping
Home-page: https://github.com/cmrschwarz/scr
Author: Christian Schwarz
Author-email: cmrs@cmrs.io
License: MIT License
Keywords: web, scrape, crawl, selenium, tor,,xpath, regex, downloader, command, shell, repl
Platform: UNKNOWN
Classifier: Programming Language :: Python :: 3
Classifier: Programming Language :: Python :: 3.9
Classifier: Programming Language :: Python :: 3.10
Classifier: License :: OSI Approved :: MIT License
Classifier: Operating System :: OS Independent
Requires-Python: >=3.9
License-File: LICENSE
Requires-Dist: lxml (~=4.8)
Requires-Dist: requests (~=2.27)
Requires-Dist: pyrfc6266 (~=1.0.1)
Requires-Dist: random-user-agent (~=1.0.1)
Requires-Dist: selenium (~=4.1.3)
Requires-Dist: tbselenium (~=0.6.2)
Requires-Dist: selenium-driver-updater (~=5.1.3)
Requires-Dist: pyreadline3 (~=3.4.1)
Requires-Dist: pywin32 (>=303) ; sys_platform == "win32"
